[
  {
    "categoria": "vegetables",
    "name": "tomato",
    "standardUnit": "unit",
    "allowedMeasures": [
      { "name": "unit", "baseValue": 1, "baseUnit": "unit" },
      { "name": "slice", "baseValue": 0.2, "baseUnit": "unit" },
      { "name": "half", "baseValue": 0.5, "baseUnit": "unit" },
      { "name": "small", "baseValue": 0.7, "baseUnit": "unit" },
      { "name": "medium", "baseValue": 1, "baseUnit": "unit" },
      { "name": "large", "baseValue": 1.3, "baseUnit": "unit" }
    ]
  },
  {
    "categoria": "vegetables",
    "name": "onion",
    "standardUnit": "unit",
    "allowedMeasures": [
      { "name": "unit", "baseValue": 1, "baseUnit": "unit" },
      { "name": "slice", "baseValue": 0.1, "baseUnit": "unit" },
      { "name": "half", "baseValue": 0.5, "baseUnit": "unit" },
      { "name": "small", "baseValue": 0.5, "baseUnit": "unit" },
      { "name": "medium", "baseValue": 1, "baseUnit": "unit" },
      { "name": "large", "baseValue": 1.7, "baseUnit": "unit" }
    ]
  },
  {
    "categoria": "vegetables",
    "name": "garlic",
    "standardUnit": "unit",
    "allowedMeasures": [
      { "name": "unit", "baseValue": 1, "baseUnit": "unit" },
      { "name": "clove", "baseValue": 0.08, "baseUnit": "unit" },
      { "name": "head", "baseValue": 1, "baseUnit": "unit" }
    ]
  },
  {
    "categoria": "vegetables",
    "name": "red bell pepper",
    "standardUnit": "unit",
    "allowedMeasures": [
      { "name": "unit", "baseValue": 1, "baseUnit": "unit" },
      { "name": "strip", "baseValue": 0.17, "baseUnit": "unit" },
      { "name": "half", "baseValue": 0.5, "baseUnit": "unit" },
      { "name": "small", "baseValue": 0.7, "baseUnit": "unit" },
      { "name": "medium", "baseValue": 1, "baseUnit": "unit" },
      { "name": "large", "baseValue": 1.4, "baseUnit": "unit" }
    ]
  },
  {
    "categoria": "vegetables",
    "name": "green bell pepper",
    "standardUnit": "unit",
    "allowedMeasures": [
      { "name": "unit", "baseValue": 1, "baseUnit": "unit" },
      { "name": "strip", "baseValue": 0.17, "baseUnit": "unit" },
      { "name": "half", "baseValue": 0.5, "baseUnit": "unit" },
      { "name": "small", "baseValue": 0.7, "baseUnit": "unit" },
      { "name": "medium", "baseValue": 1, "baseUnit": "unit" },
      { "name": "large", "baseValue": 1.4, "baseUnit": "unit" }
    ]
  },
  {
    "categoria": "vegetables",
    "name": "carrot",
    "standardUnit": "unit",
    "allowedMeasures": [
      { "name": "unit", "baseValue": 1, "baseUnit": "unit" },
      { "name": "slice", "baseValue": 0.1, "baseUnit": "unit" },
      { "name": "small", "baseValue": 0.6, "baseUnit": "unit" },
      { "name": "medium", "baseValue": 1, "baseUnit": "unit" },
      { "name": "large", "baseValue": 1.5, "baseUnit": "unit" }
    ]
  },
  {
    "categoria": "vegetables",
    "name": "zucchini",
    "standardUnit": "unit",
    "allowedMeasures": [
      { "name": "unit", "baseValue": 1, "baseUnit": "unit" },
      { "name": "slice", "baseValue": 0.1, "baseUnit": "unit" },
      { "name": "small", "baseValue": 0.6, "baseUnit": "unit" },
      { "name": "medium", "baseValue": 1, "baseUnit": "unit" },
      { "name": "large", "baseValue": 1.6, "baseUnit": "unit" }
    ]
  },
  {
    "categoria": "vegetables",
    "name": "eggplant",
    "standardUnit": "unit",
    "allowedMeasures": [
      { "name": "unit", "baseValue": 1, "baseUnit": "unit" },
      { "name": "slice", "baseValue": 0.11, "baseUnit": "unit" },
      { "name": "small", "baseValue": 0.6, "baseUnit": "unit" },
      { "name": "medium", "baseValue": 1, "baseUnit": "unit" },
      { "name": "large", "baseValue": 1.4, "baseUnit": "unit" }
    ]
  },
  {
    "categoria": "vegetables",
    "name": "cucumber",
    "standardUnit": "unit",
    "allowedMeasures": [
      { "name": "unit", "baseValue": 1, "baseUnit": "unit" },
      { "name": "slice", "baseValue": 0.05, "baseUnit": "unit" },
      { "name": "small", "baseValue": 0.5, "baseUnit": "unit" },
      { "name": "medium", "baseValue": 1, "baseUnit": "unit" },
      { "name": "large", "baseValue": 1.7, "baseUnit": "unit" }
    ]
  },
  {
    "categoria": "vegetables",
    "name": "lettuce",
    "standardUnit": "unit",
    "allowedMeasures": [
      { "name": "unit", "baseValue": 1, "baseUnit": "unit" },
      { "name": "leaf", "baseValue": 0.05, "baseUnit": "unit" },
      { "name": "head", "baseValue": 0.5, "baseUnit": "unit" },
      { "name": "piece", "baseValue": 1, "baseUnit": "unit" }
    ]
  },
  {
    "categoria": "vegetables",
    "name": "spinach",
    "standardUnit": "g",
    "allowedMeasures": [
      { "name": "g", "baseValue": 1, "baseUnit": "g" },
      { "name": "kg", "baseValue": 1000, "baseUnit": "g" },
      { "name": "bunch", "baseValue": 100, "baseUnit": "g" },
      { "name": "cup", "baseValue": 30, "baseUnit": "g" }
    ]
  },
  {
    "categoria": "vegetables",
    "name": "swiss chard",
    "standardUnit": "g",
    "allowedMeasures": [
      { "name": "g", "baseValue": 1, "baseUnit": "g" },
      { "name": "kg", "baseValue": 1000, "baseUnit": "g" },
      { "name": "bunch", "baseValue": 200, "baseUnit": "g" },
      { "name": "handfull", "baseValue": 50, "baseUnit": "g" }
    ]
  },
  {
    "categoria": "vegetables",
    "name": "broccoli",
    "standardUnit": "unit",
    "allowedMeasures": [
      { "name": "unit", "baseValue": 1, "baseUnit": "unit" },
      { "name": "floret", "baseValue": 0.1, "baseUnit": "unit" },
      { "name": "smallHead", "baseValue": 0.6, "baseUnit": "unit" },
      { "name": "bigHead", "baseValue": 1, "baseUnit": "unit" }
    ]
  },
  {
    "categoria": "vegetables",
    "name": "cauliflower",
    "standardUnit": "unit",
    "allowedMeasures": [
      { "name": "unit", "baseValue": 1, "baseUnit": "unit" },
      { "name": "floret", "baseValue": 0.08, "baseUnit": "unit" },
      { "name": "smallHead", "baseValue": 0.5, "baseUnit": "unit" },
      { "name": "bigHead", "baseValue": 1, "baseUnit": "unit" }
    ]
  },
  {
    "categoria": "vegetables",
    "name": "pumpkin",
    "standardUnit": "unit",
    "allowedMeasures": [
      { "name": "unit", "baseValue": 1, "baseUnit": "unit" },
      { "name": "piece", "baseValue": 0.4, "baseUnit": "unit" },
      { "name": "slice", "baseValue": 0.3, "baseUnit": "unit" }
    ]
  },
  {
    "categoria": "vegetables",
    "name": "leek",
    "standardUnit": "unit",
    "allowedMeasures": [
      { "name": "unit", "baseValue": 1, "baseUnit": "unit" },
      { "name": "slice", "baseValue": 0.1, "baseUnit": "unit" }
    ]
  },
  {
    "categoria": "vegetables",
    "name": "celery",
    "standardUnit": "unit",
    "allowedMeasures": [
      { "name": "unit", "baseValue": 1, "baseUnit": "unit" },
      { "name": "stalk", "baseValue": 0.5, "baseUnit": "unit" },
      { "name": "stem", "baseValue": 1, "baseUnit": "unit" }
    ]
  },
  {
    "categoria": "vegetables",
    "name": "radish",
    "standardUnit": "unit",
    "allowedMeasures": [
      { "name": "unit", "baseValue": 1, "baseUnit": "unit" }
    ]
  },
  {
    "categoria": "vegetables",
    "name": "beetroot",
    "standardUnit": "unit",
    "allowedMeasures": [
      { "name": "unit", "baseValue": 1, "baseUnit": "unit" },
      { "name": "small", "baseValue": 0.7, "baseUnit": "unit" },
      { "name": "medium", "baseValue": 1, "baseUnit": "unit" },
      { "name": "large", "baseValue": 1.7, "baseUnit": "unit" }
    ]
  },
  {
    "categoria": "vegetables",
    "name": "asparagus",
    "standardUnit": "unit",
    "allowedMeasures": [
      { "name": "unit", "baseValue": 1, "baseUnit": "unit" },
      { "name": "bunch", "baseValue": 12.5, "baseUnit": "unit" }
    ]
  },
  {
    "categoria": "vegetables",
    "name": "artichoke",
    "standardUnit": "unit",
    "allowedMeasures": [
      { "name": "unit", "baseValue": 1, "baseUnit": "unit" },
      { "name": "heart", "baseValue": 0.33, "baseUnit": "unit" }
    ]
  },
  {
    "categoria": "vegetables",
    "name": "potato",
    "standardUnit": "kg",
    "allowedMeasures": [
      { "name": "kg", "baseValue": 1, "baseUnit": "kg" },
      { "name": "g", "baseValue": 0.001, "baseUnit": "kg" },
      { "name": "small", "baseValue": 0.1, "baseUnit": "kg" },
      { "name": "medium", "baseValue": 0.2, "baseUnit": "kg" },
      { "name": "large", "baseValue": 0.3, "baseUnit": "kg" }
    ]
  },
  {
    "categoria": "legumes",
    "name": "chickpeas",
    "standardUnit": "g",
    "allowedMeasures": [
      { "name": "g", "baseValue": 1, "baseUnit": "g" },
      { "name": "kg", "baseValue": 1000, "baseUnit": "g" },
      { "name": "tablespoon", "baseValue": 15, "baseUnit": "g" },
      { "name": "cup", "baseValue": 200, "baseUnit": "g" },
      { "name": "handfull", "baseValue": 50, "baseUnit": "g" }
    ]
  },
  {
    "categoria": "legumes",
    "name": "lentils",
    "standardUnit": "g",
    "allowedMeasures": [
      { "name": "g", "baseValue": 1, "baseUnit": "g" },
      { "name": "kg", "baseValue": 1000, "baseUnit": "g" },
      { "name": "tablespoon", "baseValue": 15, "baseUnit": "g" },
      { "name": "cup", "baseValue": 200, "baseUnit": "g" },
      { "name": "handfull", "baseValue": 50, "baseUnit": "g" }
    ]
  },
  {
    "categoria": "legumes",
    "name": "white beans",
    "standardUnit": "g",
    "allowedMeasures": [
      { "name": "g", "baseValue": 1, "baseUnit": "g" },
      { "name": "kg", "baseValue": 1000, "baseUnit": "g" },
      { "name": "tablespoon", "baseValue": 20, "baseUnit": "g" },
      { "name": "cup", "baseValue": 200, "baseUnit": "g" },
      { "name": "handfull", "baseValue": 60, "baseUnit": "g" }
    ]
  },
  {
    "categoria": "legumes",
    "name": "pinto beans",
    "standardUnit": "g",
    "allowedMeasures": [
      { "name": "g", "baseValue": 1, "baseUnit": "g" },
      { "name": "kg", "baseValue": 1000, "baseUnit": "g" },
      { "name": "tablespoon", "baseValue": 20, "baseUnit": "g" },
      { "name": "cup", "baseValue": 200, "baseUnit": "g" },
      { "name": "handfull", "baseValue": 60, "baseUnit": "g" }
    ]
  },
  {
    "categoria": "legumes",
    "name": "soybeans",
    "standardUnit": "g",
    "allowedMeasures": [
      { "name": "g", "baseValue": 1, "baseUnit": "g" },
      { "name": "kg", "baseValue": 1000, "baseUnit": "g" },
      { "name": "tablespoon", "baseValue": 15, "baseUnit": "g" },
      { "name": "cup", "baseValue": 180, "baseUnit": "g" }
    ]
  },
  {
    "categoria": "legumes",
    "name": "dried peas",
    "standardUnit": "g",
    "allowedMeasures": [
      { "name": "g", "baseValue": 1, "baseUnit": "g" },
      { "name": "kg", "baseValue": 1000, "baseUnit": "g" },
      { "name": "tablespoon", "baseValue": 15, "baseUnit": "g" },
      { "name": "cup", "baseValue": 200, "baseUnit": "g" }
    ]
  },
  {
    "categoria": "legumes",
    "name": "dried fava beans",
    "standardUnit": "g",
    "allowedMeasures": [
      { "name": "g", "baseValue": 1, "baseUnit": "g" },
      { "name": "kg", "baseValue": 1000, "baseUnit": "g" },
      { "name": "tablespoon", "baseValue": 20, "baseUnit": "g" },
      { "name": "cup", "baseValue": 200, "baseUnit": "g" }
    ]
  },
  {
    "categoria": "legumes",
    "name": "green beans",
    "standardUnit": "g",
    "allowedMeasures": [
      { "name": "g", "baseValue": 1, "baseUnit": "g" },
      { "name": "kg", "baseValue": 1000, "baseUnit": "g" },
      { "name": "tablespoon", "baseValue": 20, "baseUnit": "g" },
      { "name": "cup", "baseValue": 200, "baseUnit": "g" },
      { "name": "handfull", "baseValue": 60, "baseUnit": "g" }
    ]
  },
  {
    "categoria": "grains and cereals",
    "name": "rice",
    "standardUnit": "g",
    "allowedMeasures": [
      { "name": "g", "baseValue": 1, "baseUnit": "g" },
      { "name": "kg", "baseValue": 1000, "baseUnit": "g" },
      { "name": "tablespoon", "baseValue": 15, "baseUnit": "g" },
      { "name": "cup", "baseValue": 200, "baseUnit": "g" },
      { "name": "handfull", "baseValue": 50, "baseUnit": "g" }
    ]
  },
  {
    "categoria": "grains and cereals",
    "name": "wheat",
    "standardUnit": "g",
    "allowedMeasures": [
      { "name": "g", "baseValue": 1, "baseUnit": "g" },
      { "name": "kg", "baseValue": 1000, "baseUnit": "g" },
      { "name": "tablespoon", "baseValue": 15, "baseUnit": "g" },
      { "name": "cup", "baseValue": 200, "baseUnit": "g" }
    ]
  },
  {
    "categoria": "grains and cereals",
    "name": "oats",
    "standardUnit": "g",
    "allowedMeasures": [
      { "name": "g", "baseValue": 1, "baseUnit": "g" },
      { "name": "kg", "baseValue": 1000, "baseUnit": "g" },
      { "name": "tablespoon", "baseValue": 10, "baseUnit": "g" },
      { "name": "cup", "baseValue": 100, "baseUnit": "g" }
    ]
  },
  {
    "categoria": "grains and cereals",
    "name": "corn",
    "standardUnit": "g",
    "allowedMeasures": [
      { "name": "g", "baseValue": 1, "baseUnit": "g" },
      { "name": "kg", "baseValue": 1000, "baseUnit": "g" },
      { "name": "tablespoon", "baseValue": 15, "baseUnit": "g" },
      { "name": "cup", "baseValue": 200, "baseUnit": "g" }
    ]
  },
  {
    "categoria": "grains and cereals",
    "name": "quinoa",
    "standardUnit": "g",
    "allowedMeasures": [
      { "name": "g", "baseValue": 1, "baseUnit": "g" },
      { "name": "kg", "baseValue": 1000, "baseUnit": "g" },
      { "name": "tablespoon", "baseValue": 15, "baseUnit": "g" },
      { "name": "cup", "baseValue": 180, "baseUnit": "g" }
    ]
  },
  {
    "categoria": "grains and cereals",
    "name": "barley",
    "standardUnit": "g",
    "allowedMeasures": [
      { "name": "g", "baseValue": 1, "baseUnit": "g" },
      { "name": "kg", "baseValue": 1000, "baseUnit": "g" },
      { "name": "tablespoon", "baseValue": 15, "baseUnit": "g" },
      { "name": "cup", "baseValue": 200, "baseUnit": "g" }
    ]
  },
  {
    "categoria": "grains and cereals",
    "name": "rye",
    "standardUnit": "g",
    "allowedMeasures": [
      { "name": "g", "baseValue": 1, "baseUnit": "g" },
      { "name": "kg", "baseValue": 1000, "baseUnit": "g" },
      { "name": "tablespoon", "baseValue": 15, "baseUnit": "g" },
      { "name": "cup", "baseValue": 200, "baseUnit": "g" }
    ]
  },
  {
    "categoria": "grains and cereals",
    "name": "millet",
    "standardUnit": "g",
    "allowedMeasures": [
      { "name": "g", "baseValue": 1, "baseUnit": "g" },
      { "name": "kg", "baseValue": 1000, "baseUnit": "g" },
      { "name": "tablespoon", "baseValue": 15, "baseUnit": "g" },
      { "name": "cup", "baseValue": 200, "baseUnit": "g" }
    ]
  },
  {
    "categoria": "grains and cereals",
    "name": "wheat flour",
    "standardUnit": "g",
    "allowedMeasures": [
      { "name": "g", "baseValue": 1, "baseUnit": "g" },
      { "name": "kg", "baseValue": 1000, "baseUnit": "g" },
      { "name": "tablespoon", "baseValue": 10, "baseUnit": "g" },
      { "name": "cup", "baseValue": 120, "baseUnit": "g" },
      { "name": "teaspoon", "baseValue": 3, "baseUnit": "g" }
    ]
  },
  {
    "categoria": "grains and cereals",
    "name": "corn flour",
    "standardUnit": "g",
    "allowedMeasures": [
      { "name": "g", "baseValue": 1, "baseUnit": "g" },
      { "name": "kg", "baseValue": 1000, "baseUnit": "g" },
      { "name": "tablespoon", "baseValue": 10, "baseUnit": "g" },
      { "name": "cup", "baseValue": 120, "baseUnit": "g" }
    ]
  },
  {
    "categoria": "grains and cereals",
    "name": "pasta",
    "standardUnit": "g",
    "allowedMeasures": [
      { "name": "g", "baseValue": 1, "baseUnit": "g" },
      { "name": "kg", "baseValue": 1000, "baseUnit": "g" },
      { "name": "handfull", "baseValue": 80, "baseUnit": "g" },
      { "name": "cup", "baseValue": 100, "baseUnit": "g" }
    ]
  },
  {
    "categoria": "grains and cereals",
    "name": "chinese noodles",
    "standardUnit": "g",
    "allowedMeasures": [
      { "name": "g", "baseValue": 1, "baseUnit": "g" },
      { "name": "kg", "baseValue": 1000, "baseUnit": "g" },
      { "name": "handfull", "baseValue": 80, "baseUnit": "g" },
      { "name": "cup", "baseValue": 100, "baseUnit": "g" }
    ]
  },
  {
    "categoria": "dairy and eggs",
    "name": "milk",
    "standardUnit": "ml",
    "allowedMeasures": [
      { "name": "ml", "baseValue": 1, "baseUnit": "ml" },
      { "name": "l", "baseValue": 1000, "baseUnit": "ml" },
      { "name": "tablespoon", "baseValue": 15, "baseUnit": "ml" },
      { "name": "cup", "baseValue": 250, "baseUnit": "ml" },
      { "name": "glass", "baseValue": 200, "baseUnit": "ml" },
      { "name": "drizzle", "baseValue": 10, "baseUnit": "ml" }
    ]
  },
  {
    "categoria": "dairy and eggs",
    "name": "eggs",
    "standardUnit": "unit",
    "allowedMeasures": [
      { "name": "unit", "baseValue": 1, "baseUnit": "unit" },
      { "name": "dozen", "baseValue": 12, "baseUnit": "unit" }
    ]
  },
  {
    "categoria": "dairy and eggs",
    "name": "butter",
    "standardUnit": "g",
    "allowedMeasures": [
      { "name": "g", "baseValue": 1, "baseUnit": "g" },
      { "name": "kg", "baseValue": 1000, "baseUnit": "g" },
      { "name": "tablespoon", "baseValue": 15, "baseUnit": "g" },
      { "name": "teaspoon", "baseValue": 5, "baseUnit": "g" },
      { "name": "piece", "baseValue": 25, "baseUnit": "g" }
    ]
  },
  {
    "categoria": "dairy and eggs",
    "name": "plain yogurt",
    "standardUnit": "g",
    "allowedMeasures": [
      { "name": "g", "baseValue": 1, "baseUnit": "g" },
      { "name": "kg", "baseValue": 1000, "baseUnit": "g" },
      { "name": "ml", "baseValue": 1, "baseUnit": "ml" },
      { "name": "l", "baseValue": 1000, "baseUnit": "ml" },
      { "name": "tablespoon", "baseValue": 15, "baseUnit": "g" },
      { "name": "cup", "baseValue": 250, "baseUnit": "g" },
      { "name": "container", "baseValue": 125, "baseUnit": "g" }
    ]
  },
  {
    "categoria": "dairy and eggs",
    "name": "cheese",
    "standardUnit": "g",
    "allowedMeasures": [
      { "name": "g", "baseValue": 1, "baseUnit": "g" },
      { "name": "kg", "baseValue": 1000, "baseUnit": "g" },
      { "name": "slice", "baseValue": 25, "baseUnit": "g" },
      { "name": "tablespoon", "baseValue": 10, "baseUnit": "g" },
      { "name": "cup", "baseValue": 100, "baseUnit": "g" }
    ]
  },
  {
    "categoria": "dairy and eggs",
    "name": "liquid cream",
    "standardUnit": "ml",
    "allowedMeasures": [
      { "name": "ml", "baseValue": 1, "baseUnit": "ml" },
      { "name": "l", "baseValue": 1000, "baseUnit": "ml" },
      { "name": "tablespoon", "baseValue": 15, "baseUnit": "ml" },
      { "name": "cup", "baseValue": 250, "baseUnit": "ml" },
      { "name": "drizzle", "baseValue": 10, "baseUnit": "ml" }
    ]
  },
  {
    "categoria": "dairy and eggs",
    "name": "cottage cheese",
    "standardUnit": "g",
    "allowedMeasures": [
      { "name": "g", "baseValue": 1, "baseUnit": "g" },
      { "name": "kg", "baseValue": 1000, "baseUnit": "g" },
      { "name": "tablespoon", "baseValue": 20, "baseUnit": "g" },
      { "name": "cup", "baseValue": 250, "baseUnit": "g" }
    ]
  },
  {
    "categoria": "dairy and eggs",
    "name": "milk cream",
    "standardUnit": "ml",
    "allowedMeasures": [
      { "name": "ml", "baseValue": 1, "baseUnit": "ml" },
      { "name": "l", "baseValue": 1000, "baseUnit": "ml" }
    ]
  },
  {
    "categoria": "dairy and eggs",
    "name": "shredded mozzarella",
    "standardUnit": "g",
    "allowedMeasures": [
      { "name": "g", "baseValue": 1, "baseUnit": "g" },
      { "name": "kg", "baseValue": 1000, "baseUnit": "g" }
    ]
  },
  {
    "categoria": "dairy and eggs",
    "name": "parmesan",
    "standardUnit": "g",
    "allowedMeasures": [
      { "name": "g", "baseValue": 1, "baseUnit": "g" },
      { "name": "kg", "baseValue": 1000, "baseUnit": "g" }
    ]
  },
  {
    "categoria": "dairy and eggs",
    "name": "low-fat yogurt",
    "standardUnit": "g",
    "allowedMeasures": [
      { "name": "g", "baseValue": 1, "baseUnit": "g" },
      { "name": "kg", "baseValue": 1000, "baseUnit": "g" },
      { "name": "ml", "baseValue": 1, "baseUnit": "ml" },
      { "name": "l", "baseValue": 1000, "baseUnit": "ml" },
      { "name": "tablespoon", "baseValue": 15, "baseUnit": "g" },
      { "name": "cup", "baseValue": 250, "baseUnit": "g" },
      { "name": "container", "baseValue": 125, "baseUnit": "g" }
    ]
  },
  {
    "categoria": "meat",
    "name": "chicken breast",
    "standardUnit": "g",
    "allowedMeasures": [
      { "name": "g", "baseValue": 1, "baseUnit": "g" },
      { "name": "kg", "baseValue": 1000, "baseUnit": "g" }
    ]
  },
  {
    "categoria": "meat",
    "name": "chicken drumsticks",
    "standardUnit": "g",
    "allowedMeasures": [
      { "name": "g", "baseValue": 1, "baseUnit": "g" },
      { "name": "kg", "baseValue": 1000, "baseUnit": "g" }
    ]
  },
  {
    "categoria": "meat",
    "name": "chicken wings",
    "standardUnit": "g",
    "allowedMeasures": [
      { "name": "g", "baseValue": 1, "baseUnit": "g" },
      { "name": "kg", "baseValue": 1000, "baseUnit": "g" }
    ]
  },
  {
    "categoria": "meat",
    "name": "turkey breast",
    "standardUnit": "g",
    "allowedMeasures": [
      { "name": "g", "baseValue": 1, "baseUnit": "g" },
      { "name": "kg", "baseValue": 1000, "baseUnit": "g" }
    ]
  },
  {
    "categoria": "meat",
    "name": "pork loin",
    "standardUnit": "g",
    "allowedMeasures": [
      { "name": "g", "baseValue": 1, "baseUnit": "g" },
      { "name": "kg", "baseValue": 1000, "baseUnit": "g" }
    ]
  },
  {
    "categoria": "meat",
    "name": "veal",
    "standardUnit": "g",
    "allowedMeasures": [
      { "name": "g", "baseValue": 1, "baseUnit": "g" },
      { "name": "kg", "baseValue": 1000, "baseUnit": "g" },
      { "name": "steack", "baseValue": 150, "baseUnit": "g" },
      { "name": "chop", "baseValue": 200, "baseUnit": "g" },
      { "name": "piece", "baseValue": 100, "baseUnit": "g" }
    ]
  },
  {
    "categoria": "meat",
    "name": "lamb",
    "standardUnit": "g",
    "allowedMeasures": [
      { "name": "g", "baseValue": 1, "baseUnit": "g" },
      { "name": "kg", "baseValue": 1000, "baseUnit": "g" },
      { "name": "chop", "baseValue": 150, "baseUnit": "g" },
      { "name": "steack", "baseValue": 120, "baseUnit": "g" }
    ]
  },
  {
    "categoria": "meat",
    "name": "rabbit",
    "standardUnit": "g",
    "allowedMeasures": [
      { "name": "g", "baseValue": 1, "baseUnit": "g" },
      { "name": "kg", "baseValue": 1000, "baseUnit": "g" },
      { "name": "leg", "baseValue": 200, "baseUnit": "g" },
      { "name": "piece", "baseValue": 150, "baseUnit": "g" }
    ]
  },
  {
    "categoria": "meat",
    "name": "mixed minced meat",
    "standardUnit": "g",
    "allowedMeasures": [
      { "name": "g", "baseValue": 1, "baseUnit": "g" },
      { "name": "kg", "baseValue": 1000, "baseUnit": "g" },
      { "name": "meatBall", "baseValue": 30, "baseUnit": "g" },
      { "name": "burguer", "baseValue": 100, "baseUnit": "g" },
      { "name": "handfull", "baseValue": 80, "baseUnit": "g" }
    ]
  },
  {
    "categoria": "meat",
    "name": "beef minced meat",
    "standardUnit": "g",
    "allowedMeasures": [
      { "name": "g", "baseValue": 1, "baseUnit": "g" },
      { "name": "kg", "baseValue": 1000, "baseUnit": "g" },
      { "name": "meatBall", "baseValue": 30, "baseUnit": "g" },
      { "name": "burguer", "baseValue": 100, "baseUnit": "g" }
    ]
  },
  {
    "categoria": "meat",
    "name": "pork minced meat",
    "standardUnit": "g",
    "allowedMeasures": [
      { "name": "g", "baseValue": 1, "baseUnit": "g" },
      { "name": "kg", "baseValue": 1000, "baseUnit": "g" },
      { "name": "meatBall", "baseValue": 30, "baseUnit": "g" },
      { "name": "burguer", "baseValue": 100, "baseUnit": "g" }
    ]
  },
  {
    "categoria": "meat",
    "name": "bacon",
    "standardUnit": "g",
    "allowedMeasures": [
      { "name": "g", "baseValue": 1, "baseUnit": "g" },
      { "name": "kg", "baseValue": 1000, "baseUnit": "g" }
    ]
  },
  {
    "categoria": "meat",
    "name": "york ham",
    "standardUnit": "packet",
    "allowedMeasures": [
      { "name": "packet", "baseValue": 1, "baseUnit": "packet" },
      { "name": "slice", "baseValue": 0.05, "baseUnit": "packet" }
    ]
  },
  {
    "categoria": "meat",
    "name": "cheeks",
    "standardUnit": "g",
    "allowedMeasures": [
      { "name": "g", "baseValue": 1, "baseUnit": "g" },
      { "name": "kg", "baseValue": 1000, "baseUnit": "g" }
    ]
  },
  {
    "categoria": "meat",
    "name": "sausage",
    "standardUnit": "g",
    "allowedMeasures": [
      { "name": "g", "baseValue": 1, "baseUnit": "g" },
      { "name": "kg", "baseValue": 1000, "baseUnit": "g" }
    ]
  },
  {
    "categoria": "meat",
    "name": "frankfurts",
    "standardUnit": "unit",
    "allowedMeasures": [
      { "name": "unit", "baseValue": 1, "baseUnit": "unit" },
      { "name": "packet", "baseValue": 10, "baseUnit": "unit" }
    ]
  },
  {
    "categoria": "fish and seafood",
    "name": "hake",
    "standardUnit": "g",
    "allowedMeasures": [
      { "name": "g", "baseValue": 1, "baseUnit": "g" },
      { "name": "kg", "baseValue": 1000, "baseUnit": "g" },
      { "name": "filet", "baseValue": 150, "baseUnit": "g" },
      { "name": "slice", "baseValue": 100, "baseUnit": "g" }
    ]
  },
  {
    "categoria": "fish and seafood",
    "name": "salmon",
    "standardUnit": "g",
    "allowedMeasures": [
      { "name": "g", "baseValue": 1, "baseUnit": "g" },
      { "name": "kg", "baseValue": 1000, "baseUnit": "g" },
      { "name": "filet", "baseValue": 200, "baseUnit": "g" },
      { "name": "slice", "baseValue": 150, "baseUnit": "g" },
      { "name": "slice", "baseValue": 50, "baseUnit": "g" }
    ]
  },
  {
    "categoria": "fish and seafood",
    "name": "tuna",
    "standardUnit": "g",
    "allowedMeasures": [
      { "name": "g", "baseValue": 1, "baseUnit": "g" },
      { "name": "kg", "baseValue": 1000, "baseUnit": "g" },
      { "name": "filet", "baseValue": 200, "baseUnit": "g" },
      { "name": "smallCan", "baseValue": 80, "baseUnit": "g" },
      { "name": "largeCan", "baseValue": 160, "baseUnit": "g" }
    ]
  },
  {
    "categoria": "fish and seafood",
    "name": "cod",
    "standardUnit": "g",
    "allowedMeasures": [
      { "name": "g", "baseValue": 1, "baseUnit": "g" },
      { "name": "kg", "baseValue": 1000, "baseUnit": "g" },
      { "name": "filet", "baseValue": 150, "baseUnit": "g" },
      { "name": "slice", "baseValue": 100, "baseUnit": "g" }
    ]
  },
  {
    "categoria": "fish and seafood",
    "name": "shrimp",
    "standardUnit": "g",
    "allowedMeasures": [
      { "name": "g", "baseValue": 1, "baseUnit": "g" },
      { "name": "kg", "baseValue": 1000, "baseUnit": "g" },
      { "name": "unit", "baseValue": 10, "baseUnit": "g" },
      { "name": "handfull", "baseValue": 50, "baseUnit": "g" }
    ]
  },
  {
    "categoria": "fish and seafood",
    "name": "mussels",
    "standardUnit": "g",
    "allowedMeasures": [
      { "name": "g", "baseValue": 1, "baseUnit": "g" },
      { "name": "kg", "baseValue": 1000, "baseUnit": "g" },
      { "name": "unit", "baseValue": 15, "baseUnit": "g" },
      { "name": "handfull", "baseValue": 100, "baseUnit": "g" }
    ]
  },
  {
    "categoria": "fish and seafood",
    "name": "squid",
    "standardUnit": "g",
    "allowedMeasures": [
      { "name": "g", "baseValue": 1, "baseUnit": "g" },
      { "name": "kg", "baseValue": 1000, "baseUnit": "g" },
      { "name": "unit", "baseValue": 50, "baseUnit": "g" },
      { "name": "ring", "baseValue": 20, "baseUnit": "g" }
    ]
  },
  {
    "categoria": "fish and seafood",
    "name": "octopus",
    "standardUnit": "g",
    "allowedMeasures": [
      { "name": "g", "baseValue": 1, "baseUnit": "g" },
      { "name": "kg", "baseValue": 1000, "baseUnit": "g" },
      { "name": "tentacle", "baseValue": 100, "baseUnit": "g" },
      { "name": "slice", "baseValue": 50, "baseUnit": "g" }
    ]
  },
  {
    "categoria": "fish and seafood",
    "name": "panga",
    "standardUnit": "g",
    "allowedMeasures": [
      { "name": "g", "baseValue": 1, "baseUnit": "g" },
      { "name": "kg", "baseValue": 1000, "baseUnit": "g" },
      { "name": "filet", "baseValue": 150, "baseUnit": "g" },
      { "name": "slice", "baseValue": 100, "baseUnit": "g" }
    ]
  },
  {
    "categoria": "spices and seasonings",
    "name": "salt",
    "standardUnit": "g",
    "allowedMeasures": [
      { "name": "g", "baseValue": 1, "baseUnit": "g" },
      { "name": "kg", "baseValue": 1000, "baseUnit": "g" },
      { "name": "pinch", "baseValue": 1, "baseUnit": "g" },
      { "name": "teaspoon", "baseValue": 5, "baseUnit": "g" },
      { "name": "tablespoon", "baseValue": 15, "baseUnit": "g" }
    ]
  },
  {
    "categoria": "spices and seasonings",
    "name": "black pepper",
    "standardUnit": "g",
    "allowedMeasures": [
      { "name": "g", "baseValue": 1, "baseUnit": "g" },
      { "name": "kg", "baseValue": 1000, "baseUnit": "g" },
      { "name": "pinch", "baseValue": 0.5, "baseUnit": "g" },
      { "name": "teaspoon", "baseValue": 2, "baseUnit": "g" },
      { "name": "ground", "baseValue": 1, "baseUnit": "g" }
    ]
  },
  {
    "categoria": "spices and seasonings",
    "name": "spicy paprika",
    "standardUnit": "g",
    "allowedMeasures": [
      { "name": "g", "baseValue": 1, "baseUnit": "g" },
      { "name": "kg", "baseValue": 1000, "baseUnit": "g" },
      { "name": "teaspoon", "baseValue": 2, "baseUnit": "g" },
      { "name": "tablespoon", "baseValue": 8, "baseUnit": "g" }
    ]
  },
  {
    "categoria": "spices and seasonings",
    "name": "cumin",
    "standardUnit": "g",
    "allowedMeasures": [
      { "name": "g", "baseValue": 1, "baseUnit": "g" },
      { "name": "kg", "baseValue": 1000, "baseUnit": "g" },
      { "name": "teaspoon", "baseValue": 3, "baseUnit": "g" },
      { "name": "tablespoon", "baseValue": 10, "baseUnit": "g" }
    ]
  },
  {
    "categoria": "spices and seasonings",
    "name": "oregano",
    "standardUnit": "g",
    "allowedMeasures": [
      { "name": "g", "baseValue": 1, "baseUnit": "g" },
      { "name": "kg", "baseValue": 1000, "baseUnit": "g" },
      { "name": "teaspoon", "baseValue": 1, "baseUnit": "g" },
      { "name": "tablespoon", "baseValue": 3, "baseUnit": "g" },
      { "name": "spring", "baseValue": 2, "baseUnit": "g" }
    ]
  },
  {
    "categoria": "spices and seasonings",
    "name": "thyme",
    "standardUnit": "g",
    "allowedMeasures": [
      { "name": "g", "baseValue": 1, "baseUnit": "g" },
      { "name": "kg", "baseValue": 1000, "baseUnit": "g" },
      { "name": "spring", "baseValue": 1, "baseUnit": "g" },
      { "name": "teaspoon", "baseValue": 1, "baseUnit": "g" }
    ]
  },
  {
    "categoria": "spices and seasonings",
    "name": "rosemary",
    "standardUnit": "g",
    "allowedMeasures": [
      { "name": "g", "baseValue": 1, "baseUnit": "g" },
      { "name": "kg", "baseValue": 1000, "baseUnit": "g" },
      { "name": "spring", "baseValue": 2, "baseUnit": "g" },
      { "name": "teaspoon", "baseValue": 1, "baseUnit": "g" }
    ]
  },
  {
    "categoria": "spices and seasonings",
    "name": "basil",
    "standardUnit": "g",
    "allowedMeasures": [
      { "name": "g", "baseValue": 1, "baseUnit": "g" },
      { "name": "kg", "baseValue": 1000, "baseUnit": "g" },
      { "name": "leaf", "baseValue": 0.5, "baseUnit": "g" },
      { "name": "spring", "baseValue": 3, "baseUnit": "g" },
      { "name": "teaspoon", "baseValue": 1, "baseUnit": "g" }
    ]
  },
  {
    "categoria": "spices and seasonings",
    "name": "parsley",
    "standardUnit": "g",
    "allowedMeasures": [
      { "name": "g", "baseValue": 1, "baseUnit": "g" },
      { "name": "kg", "baseValue": 1000, "baseUnit": "g" },
      { "name": "spring", "baseValue": 2, "baseUnit": "g" },
      { "name": "tablespoon", "baseValue": 5, "baseUnit": "g" }
    ]
  },
  {
    "categoria": "spices and seasonings",
    "name": "coriander",
    "standardUnit": "g",
    "allowedMeasures": [
      { "name": "g", "baseValue": 1, "baseUnit": "g" },
      { "name": "kg", "baseValue": 1000, "baseUnit": "g" },
      { "name": "spring", "baseValue": 2, "baseUnit": "g" },
      { "name": "tablespoon", "baseValue": 5, "baseUnit": "g" }
    ]
  },
  {
    "categoria": "spices and seasonings",
    "name": "cinnamon",
    "standardUnit": "g",
    "allowedMeasures": [
      { "name": "g", "baseValue": 1, "baseUnit": "g" },
      { "name": "kg", "baseValue": 1000, "baseUnit": "g" },
      { "name": "stick", "baseValue": 3, "baseUnit": "g" },
      { "name": "teaspoon", "baseValue": 2, "baseUnit": "g" }
    ]
  },
  {
    "categoria": "spices and seasonings",
    "name": "clove",
    "standardUnit": "g",
    "allowedMeasures": [
      { "name": "g", "baseValue": 1, "baseUnit": "g" },
      { "name": "kg", "baseValue": 1000, "baseUnit": "g" },
      { "name": "unit", "baseValue": 0.1, "baseUnit": "g" },
      { "name": "teaspoon", "baseValue": 2, "baseUnit": "g" }
    ]
  },
  {
    "categoria": "spices and seasonings",
    "name": "nutmeg",
    "standardUnit": "g",
    "allowedMeasures": [
      { "name": "g", "baseValue": 1, "baseUnit": "g" },
      { "name": "kg", "baseValue": 1000, "baseUnit": "g" },
      { "name": "grating", "baseValue": 0.5, "baseUnit": "g" },
      { "name": "teaspoon", "baseValue": 2, "baseUnit": "g" }
    ]
  },
  {
    "categoria": "spices and seasonings",
    "name": "turmeric",
    "standardUnit": "g",
    "allowedMeasures": [
      { "name": "g", "baseValue": 1, "baseUnit": "g" },
      { "name": "kg", "baseValue": 1000, "baseUnit": "g" },
      { "name": "teaspoon", "baseValue": 2, "baseUnit": "g" },
      { "name": "tablespoon", "baseValue": 8, "baseUnit": "g" }
    ]
  },
  {
    "categoria": "spices and seasonings",
    "name": "ginger",
    "standardUnit": "g",
    "allowedMeasures": [
      { "name": "g", "baseValue": 1, "baseUnit": "g" },
      { "name": "kg", "baseValue": 1000, "baseUnit": "g" },
      { "name": "slice", "baseValue": 5, "baseUnit": "g" },
      { "name": "teaspoon", "baseValue": 2, "baseUnit": "g" }
    ]
  },
  {
    "categoria": "spices and seasonings",
    "name": "vanilla",
    "standardUnit": "ml",
    "allowedMeasures": [
      { "name": "ml", "baseValue": 1, "baseUnit": "ml" },
      { "name": "l", "baseValue": 1000, "baseUnit": "ml" },
      { "name": "g", "baseValue": 1, "baseUnit": "g" },
      { "name": "kg", "baseValue": 1000, "baseUnit": "g" },
      { "name": "bean", "baseValue": 2, "baseUnit": "g" },
      { "name": "teaspoon", "baseValue": 5, "baseUnit": "ml" }
    ]
  },
  {
    "categoria": "spices and seasonings",
    "name": "saffron",
    "standardUnit": "g",
    "allowedMeasures": [
      { "name": "g", "baseValue": 1, "baseUnit": "g" },
      { "name": "kg", "baseValue": 1000, "baseUnit": "g" },
      { "name": "thread", "baseValue": 0.01, "baseUnit": "g" },
      { "name": "pinch", "baseValue": 0.1, "baseUnit": "g" }
    ]
  },
  {
    "categoria": "spices and seasonings",
    "name": "bay leaf",
    "standardUnit": "leaf",
    "allowedMeasures": [
      { "name": "leaf", "baseValue": 1, "baseUnit": "unit" }
    ]
  },
  {
    "categoria": "spices and seasonings",
    "name": "tahini",
    "standardUnit": "g",
    "allowedMeasures": [
      { "name": "g", "baseValue": 1, "baseUnit": "g" },
      { "name": "kg", "baseValue": 1000, "baseUnit": "g" },
      { "name": "pinch", "baseValue": 1, "baseUnit": "g" },
      { "name": "teaspoon", "baseValue": 5, "baseUnit": "g" }
    ]
  },
  {
    "categoria": "spices and seasonings",
    "name": "sweet paprika",
    "standardUnit": "g",
    "allowedMeasures": [
      { "name": "g", "baseValue": 1, "baseUnit": "g" },
      { "name": "kg", "baseValue": 1000, "baseUnit": "g" },
      { "name": "teaspoon", "baseValue": 2, "baseUnit": "g" },
      { "name": "tablespoon", "baseValue": 8, "baseUnit": "g" }
    ]
  },
  {
    "categoria": "oils and fats",
    "name": "olive oil",
    "standardUnit": "ml",
    "allowedMeasures": [
      { "name": "ml", "baseValue": 1, "baseUnit": "ml" },
      { "name": "l", "baseValue": 1000, "baseUnit": "ml" },
      { "name": "drizzle", "baseValue": 10, "baseUnit": "ml" },
      { "name": "tablespoon", "baseValue": 15, "baseUnit": "ml" },
      { "name": "teaspoon", "baseValue": 5, "baseUnit": "ml" },
      { "name": "thread", "baseValue": 5, "baseUnit": "ml" }
    ]
  },
  {
    "categoria": "oils and fats",
    "name": "sunflower oil",
    "standardUnit": "ml",
    "allowedMeasures": [
      { "name": "ml", "baseValue": 1, "baseUnit": "ml" },
      { "name": "l", "baseValue": 1000, "baseUnit": "ml" },
      { "name": "drizzle", "baseValue": 10, "baseUnit": "ml" },
      { "name": "tablespoon", "baseValue": 15, "baseUnit": "ml" },
      { "name": "teaspoon", "baseValue": 5, "baseUnit": "ml" }
    ]
  },
  {
    "categoria": "oils and fats",
    "name": "corn oil",
    "standardUnit": "ml",
    "allowedMeasures": [
      { "name": "ml", "baseValue": 1, "baseUnit": "ml" },
      { "name": "l", "baseValue": 1000, "baseUnit": "ml" },
      { "name": "drizzle", "baseValue": 10, "baseUnit": "ml" },
      { "name": "tablespoon", "baseValue": 15, "baseUnit": "ml" }
    ]
  },
  {
    "categoria": "oils and fats",
    "name": "lard",
    "standardUnit": "g",
    "allowedMeasures": [
      { "name": "g", "baseValue": 1, "baseUnit": "g" },
      { "name": "kg", "baseValue": 1000, "baseUnit": "g" },
      { "name": "tablespoon", "baseValue": 15, "baseUnit": "g" },
      { "name": "piece", "baseValue": 25, "baseUnit": "g" }
    ]
  },
  {
    "categoria": "oils and fats",
    "name": "coconut oil",
    "standardUnit": "ml",
    "allowedMeasures": [
      { "name": "ml", "baseValue": 1, "baseUnit": "ml" },
      { "name": "l", "baseValue": 1000, "baseUnit": "ml" },
      { "name": "g", "baseValue": 1, "baseUnit": "g" },
      { "name": "kg", "baseValue": 1000, "baseUnit": "g" },
      { "name": "tablespoon", "baseValue": 15, "baseUnit": "ml" },
      { "name": "teaspoon", "baseValue": 5, "baseUnit": "ml" }
    ]
  },
  {
    "categoria": "nuts and seeds",
    "name": "almonds",
    "standardUnit": "g",
    "allowedMeasures": [
      { "name": "g", "baseValue": 1, "baseUnit": "g" },
      { "name": "kg", "baseValue": 1000, "baseUnit": "g" },
      { "name": "unit", "baseValue": 1, "baseUnit": "g" },
      { "name": "handfull", "baseValue": 30, "baseUnit": "g" },
      { "name": "cup", "baseValue": 150, "baseUnit": "g" }
    ]
  },
  {
    "categoria": "nuts and seeds",
    "name": "walnuts",
    "standardUnit": "g",
    "allowedMeasures": [
      { "name": "g", "baseValue": 1, "baseUnit": "g" },
      { "name": "kg", "baseValue": 1000, "baseUnit": "g" },
      { "name": "half", "baseValue": 2, "baseUnit": "g" },
      { "name": "unit", "baseValue": 5, "baseUnit": "g" },
      { "name": "handfull", "baseValue": 40, "baseUnit": "g" }
    ]
  },
  {
    "categoria": "nuts and seeds",
    "name": "hazelnuts",
    "standardUnit": "g",
    "allowedMeasures": [
      { "name": "g", "baseValue": 1, "baseUnit": "g" },
      { "name": "kg", "baseValue": 1000, "baseUnit": "g" },
      { "name": "unit", "baseValue": 1, "baseUnit": "g" },
      { "name": "handfull", "baseValue": 30, "baseUnit": "g" }
    ]
  },
  {
    "categoria": "nuts and seeds",
    "name": "pine nuts",
    "standardUnit": "g",
    "allowedMeasures": [
      { "name": "g", "baseValue": 1, "baseUnit": "g" },
      { "name": "kg", "baseValue": 1000, "baseUnit": "g" },
      { "name": "tablespoon", "baseValue": 10, "baseUnit": "g" },
      { "name": "handfull", "baseValue": 20, "baseUnit": "g" }
    ]
  },
  {
    "categoria": "nuts and seeds",
    "name": "peanuts",
    "standardUnit": "g",
    "allowedMeasures": [
      { "name": "g", "baseValue": 1, "baseUnit": "g" },
      { "name": "kg", "baseValue": 1000, "baseUnit": "g" },
      { "name": "unit", "baseValue": 1, "baseUnit": "g" },
      { "name": "handfull", "baseValue": 40, "baseUnit": "g" }
    ]
  },
  {
    "categoria": "nuts and seeds",
    "name": "sunflower seeds",
    "standardUnit": "g",
    "allowedMeasures": [
      { "name": "g", "baseValue": 1, "baseUnit": "g" },
      { "name": "kg", "baseValue": 1000, "baseUnit": "g" },
      { "name": "tablespoon", "baseValue": 10, "baseUnit": "g" },
      { "name": "handfull", "baseValue": 25, "baseUnit": "g" }
    ]
  },
  {
    "categoria": "nuts and seeds",
    "name": "pumpkin seeds",
    "standardUnit": "g",
    "allowedMeasures": [
      { "name": "g", "baseValue": 1, "baseUnit": "g" },
      { "name": "kg", "baseValue": 1000, "baseUnit": "g" },
      { "name": "tablespoon", "baseValue": 10, "baseUnit": "g" },
      { "name": "handfull", "baseValue": 25, "baseUnit": "g" }
    ]
  },
  {
    "categoria": "nuts and seeds",
    "name": "sesame seeds",
    "standardUnit": "g",
    "allowedMeasures": [
      { "name": "g", "baseValue": 1, "baseUnit": "g" },
      { "name": "kg", "baseValue": 1000, "baseUnit": "g" },
      { "name": "teaspoon", "baseValue": 3, "baseUnit": "g" },
      { "name": "tablespoon", "baseValue": 10, "baseUnit": "g" }
    ]
  },
  {
    "categoria": "nuts and seeds",
    "name": "flax seeds",
    "standardUnit": "g",
    "allowedMeasures": [
      { "name": "g", "baseValue": 1, "baseUnit": "g" },
      { "name": "kg", "baseValue": 1000, "baseUnit": "g" },
      { "name": "tablespoon", "baseValue": 10, "baseUnit": "g" },
      { "name": "teaspoon", "baseValue": 3, "baseUnit": "g" }
    ]
  },
  {
    "categoria": "nuts and seeds",
    "name": "chia seeds",
    "standardUnit": "g",
    "allowedMeasures": [
      { "name": "g", "baseValue": 1, "baseUnit": "g" },
      { "name": "kg", "baseValue": 1000, "baseUnit": "g" },
      { "name": "tablespoon", "baseValue": 10, "baseUnit": "g" },
      { "name": "teaspoon", "baseValue": 3, "baseUnit": "g" }
    ]
  },
  {
    "categoria": "fruits",
    "name": "lemon",
    "standardUnit": "unit",
    "allowedMeasures": [
      { "name": "unit", "baseValue": 1, "baseUnit": "unit" },
      { "name": "slice", "baseValue": 0.08, "baseUnit": "unit" },
      { "name": "half", "baseValue": 0.5, "baseUnit": "unit" },
      { "name": "small", "baseValue": 0.7, "baseUnit": "unit" },
      { "name": "medium", "baseValue": 1, "baseUnit": "unit" }
    ]
  },
  {
    "categoria": "fruits",
    "name": "orange",
    "standardUnit": "unit",
    "allowedMeasures": [
      { "name": "unit", "baseValue": 1, "baseUnit": "unit" },
      { "name": "segment", "baseValue": 0.1, "baseUnit": "unit" },
      { "name": "half", "baseValue": 0.5, "baseUnit": "unit" },
      { "name": "small", "baseValue": 0.75, "baseUnit": "unit" },
      { "name": "medium", "baseValue": 1, "baseUnit": "unit" },
      { "name": "large", "baseValue": 1.5, "baseUnit": "unit" }
    ]
  },
  {
    "categoria": "fruits",
    "name": "apple",
    "standardUnit": "unit",
    "allowedMeasures": [
      { "name": "unit", "baseValue": 1, "baseUnit": "unit" },
      { "name": "slice", "baseValue": 0.11, "baseUnit": "unit" },
      { "name": "half", "baseValue": 0.5, "baseUnit": "unit" },
      { "name": "small", "baseValue": 0.7, "baseUnit": "unit" },
      { "name": "medium", "baseValue": 1, "baseUnit": "unit" },
      { "name": "large", "baseValue": 1.4, "baseUnit": "unit" }
    ]
  },
  {
    "categoria": "fruits",
    "name": "banana",
    "standardUnit": "unit",
    "allowedMeasures": [
      { "name": "unit", "baseValue": 1, "baseUnit": "unit" },
      { "name": "slice", "baseValue": 0.1, "baseUnit": "unit" },
      { "name": "small", "baseValue": 0.7, "baseUnit": "unit" },
      { "name": "medium", "baseValue": 1, "baseUnit": "unit" },
      { "name": "large", "baseValue": 1.3, "baseUnit": "unit" }
    ]
  },
  {
    "categoria": "fruits",
    "name": "pear",
    "standardUnit": "unit",
    "allowedMeasures": [
      { "name": "unit", "baseValue": 1, "baseUnit": "unit" },
      { "name": "slice", "baseValue": 0.11, "baseUnit": "unit" },
      { "name": "half", "baseValue": 0.5, "baseUnit": "unit" },
      { "name": "small", "baseValue": 0.7, "baseUnit": "unit" },
      { "name": "medium", "baseValue": 1, "baseUnit": "unit" },
      { "name": "large", "baseValue": 1.4, "baseUnit": "unit" }
    ]
  },
  {
    "categoria": "fruits",
    "name": "grape",
    "standardUnit": "g",
    "allowedMeasures": [
      { "name": "g", "baseValue": 1, "baseUnit": "g" },
      { "name": "kg", "baseValue": 1000, "baseUnit": "g" },
      { "name": "unit", "baseValue": 5, "baseUnit": "g" },
      { "name": "smallBunch", "baseValue": 200, "baseUnit": "g" },
      { "name": "largeBunch", "baseValue": 500, "baseUnit": "g" }
    ]
  },
  {
    "categoria": "fruits",
    "name": "peach",
    "standardUnit": "unit",
    "allowedMeasures": [
      { "name": "unit", "baseValue": 1, "baseUnit": "unit" },
      { "name": "half", "baseValue": 0.5, "baseUnit": "unit" },
      { "name": "small", "baseValue": 0.8, "baseUnit": "unit" },
      { "name": "medium", "baseValue": 1, "baseUnit": "unit" },
      { "name": "large", "baseValue": 1.3, "baseUnit": "unit" }
    ]
  },
  {
    "categoria": "fruits",
    "name": "apricot",
    "standardUnit": "unit",
    "allowedMeasures": [
      { "name": "unit", "baseValue": 1, "baseUnit": "unit" },
      { "name": "half", "baseValue": 0.5, "baseUnit": "unit" },
      { "name": "small", "baseValue": 0.7, "baseUnit": "unit" },
      { "name": "medium", "baseValue": 1, "baseUnit": "unit" }
    ]
  },
  {
    "categoria": "fruits",
    "name": "plum",
    "standardUnit": "unit",
    "allowedMeasures": [
      { "name": "unit", "baseValue": 1, "baseUnit": "unit" },
      { "name": "small", "baseValue": 0.7, "baseUnit": "unit" },
      { "name": "medium", "baseValue": 1, "baseUnit": "unit" },
      { "name": "large", "baseValue": 1.3, "baseUnit": "unit" }
    ]
  },
  {
    "categoria": "fruits",
    "name": "strawberry",
    "standardUnit": "g",
    "allowedMeasures": [
      { "name": "g", "baseValue": 1, "baseUnit": "g" },
      { "name": "kg", "baseValue": 1000, "baseUnit": "g" },
      { "name": "unit", "baseValue": 15, "baseUnit": "g" },
      { "name": "handfull", "baseValue": 100, "baseUnit": "g" }
    ]
  },
  {
    "categoria": "fruits",
    "name": "watermelon",
    "standardUnit": "unit",
    "allowedMeasures": [
      { "name": "unit", "baseValue": 1, "baseUnit": "unit" },
      { "name": "slice", "baseValue": 0.1, "baseUnit": "unit" },
      { "name": "piece", "baseValue": 0.07, "baseUnit": "unit" }
    ]
  },
  {
    "categoria": "fruits",
    "name": "melon",
    "standardUnit": "unit",
    "allowedMeasures": [
      { "name": "unit", "baseValue": 1, "baseUnit": "unit" },
      { "name": "slice", "baseValue": 0.125, "baseUnit": "unit" },
      { "name": "piece", "baseValue": 0.08, "baseUnit": "unit" }
    ]
  },
  {
    "categoria": "liquids and beverages",
    "name": "water",
    "standardUnit": "ml",
    "allowedMeasures": [
      { "name": "ml", "baseValue": 1, "baseUnit": "ml" },
      { "name": "l", "baseValue": 1000, "baseUnit": "ml" },
      { "name": "glass", "baseValue": 200, "baseUnit": "ml" },
      { "name": "cup", "baseValue": 250, "baseUnit": "ml" },
      { "name": "splash", "baseValue": 50, "baseUnit": "ml" }
    ]
  },
  {
    "categoria": "liquids and beverages",
    "name": "white wine",
    "standardUnit": "ml",
    "allowedMeasures": [
      { "name": "ml", "baseValue": 1, "baseUnit": "ml" },
      { "name": "l", "baseValue": 1000, "baseUnit": "ml" },
      { "name": "glass", "baseValue": 100, "baseUnit": "ml" },
      { "name": "whineGlass", "baseValue": 150, "baseUnit": "ml" },
      { "name": "splash", "baseValue": 50, "baseUnit": "ml" }
    ]
  },
  {
    "categoria": "liquids and beverages",
    "name": "red wine",
    "standardUnit": "ml",
    "allowedMeasures": [
      { "name": "ml", "baseValue": 1, "baseUnit": "ml" },
      { "name": "l", "baseValue": 1000, "baseUnit": "ml" },
      { "name": "glass", "baseValue": 100, "baseUnit": "ml" },
      { "name": "whineGlass", "baseValue": 150, "baseUnit": "ml" },
      { "name": "splash", "baseValue": 50, "baseUnit": "ml" }
    ]
  },
  {
    "categoria": "liquids and beverages",
    "name": "vinegar",
    "standardUnit": "ml",
    "allowedMeasures": [
      { "name": "ml", "baseValue": 1, "baseUnit": "ml" },
      { "name": "l", "baseValue": 1000, "baseUnit": "ml" },
      { "name": "tablespoon", "baseValue": 15, "baseUnit": "ml" },
      { "name": "teaspoon", "baseValue": 5, "baseUnit": "ml" },
      { "name": "splash", "baseValue": 10, "baseUnit": "ml" }
    ]
  },
  {
    "categoria": "liquids and beverages",
    "name": "apple cider vinegar",
    "standardUnit": "ml",
    "allowedMeasures": [
      { "name": "ml", "baseValue": 1, "baseUnit": "ml" },
      { "name": "l", "baseValue": 1000, "baseUnit": "ml" },
      { "name": "tablespoon", "baseValue": 15, "baseUnit": "ml" },
      { "name": "teaspoon", "baseValue": 5, "baseUnit": "ml" }
    ]
  },
  {
    "categoria": "liquids and beverages",
    "name": "chicken broth",
    "standardUnit": "ml",
    "allowedMeasures": [
      { "name": "ml", "baseValue": 1, "baseUnit": "ml" },
      { "name": "l", "baseValue": 1000, "baseUnit": "ml" },
      { "name": "cup", "baseValue": 250, "baseUnit": "ml" },
      { "name": "glass", "baseValue": 200, "baseUnit": "ml" }
    ]
  },
  {
    "categoria": "liquids and beverages",
    "name": "vegetable broth",
    "standardUnit": "ml",
    "allowedMeasures": [
      { "name": "ml", "baseValue": 1, "baseUnit": "ml" },
      { "name": "l", "baseValue": 1000, "baseUnit": "ml" },
      { "name": "cup", "baseValue": 250, "baseUnit": "ml" },
      { "name": "glass", "baseValue": 200, "baseUnit": "ml" }
    ]
  },
  {
    "categoria": "liquids and beverages",
    "name": "fish broth",
    "standardUnit": "ml",
    "allowedMeasures": [
      { "name": "ml", "baseValue": 1, "baseUnit": "ml" },
      { "name": "l", "baseValue": 1000, "baseUnit": "ml" },
      { "name": "cup", "baseValue": 250, "baseUnit": "ml" },
      { "name": "glass", "baseValue": 200, "baseUnit": "ml" }
    ]
  },
  {
    "categoria": "liquids and beverages",
    "name": "beer",
    "standardUnit": "ml",
    "allowedMeasures": [
      { "name": "ml", "baseValue": 1, "baseUnit": "ml" },
      { "name": "l", "baseValue": 1000, "baseUnit": "ml" },
      { "name": "glass", "baseValue": 200, "baseUnit": "ml" },
      { "name": "bottle", "baseValue": 330, "baseUnit": "ml" },
      { "name": "smallCan", "baseValue": 330, "baseUnit": "ml" }
    ]
  },
  {
    "categoria": "liquids and beverages",
    "name": "brandy",
    "standardUnit": "ml",
    "allowedMeasures": [
      { "name": "ml", "baseValue": 1, "baseUnit": "ml" },
      { "name": "l", "baseValue": 1000, "baseUnit": "ml" },
      { "name": "shot", "baseValue": 30, "baseUnit": "ml" },
      { "name": "glass", "baseValue": 50, "baseUnit": "ml" }
    ]
  },
  {
    "categoria": "liquids and beverages",
    "name": "orange juice",
    "standardUnit": "ml",
    "allowedMeasures": [
      { "name": "ml", "baseValue": 1, "baseUnit": "ml" },
      { "name": "l", "baseValue": 1000, "baseUnit": "ml" },
      { "name": "glass", "baseValue": 200, "baseUnit": "ml" },
      { "name": "cup", "baseValue": 250, "baseUnit": "ml" }
    ]
  },
  {
    "categoria": "other",
    "name": "sugar",
    "standardUnit": "g",
    "allowedMeasures": [
      { "name": "g", "baseValue": 1, "baseUnit": "g" },
      { "name": "kg", "baseValue": 1000, "baseUnit": "g" },
      { "name": "teaspoon", "baseValue": 5, "baseUnit": "g" },
      { "name": "tablespoon", "baseValue": 15, "baseUnit": "g" },
      { "name": "cup", "baseValue": 200, "baseUnit": "g" }
    ]
  },
  {
    "categoria": "other",
    "name": "honey",
    "standardUnit": "g",
    "allowedMeasures": [
      { "name": "g", "baseValue": 1, "baseUnit": "g" },
      { "name": "kg", "baseValue": 1000, "baseUnit": "g" },
      { "name": "ml", "baseValue": 1.4, "baseUnit": "ml" },
      { "name": "l", "baseValue": 1400, "baseUnit": "ml" },
      { "name": "teaspoon", "baseValue": 7, "baseUnit": "g" },
      { "name": "tablespoon", "baseValue": 21, "baseUnit": "g" },
      { "name": "thread", "baseValue": 10, "baseUnit": "g" }
    ]
  },
  {
    "categoria": "other",
    "name": "yeast",
    "standardUnit": "g",
    "allowedMeasures": [
      { "name": "g", "baseValue": 1, "baseUnit": "g" },
      { "name": "kg", "baseValue": 1000, "baseUnit": "g" },
      { "name": "packet", "baseValue": 7, "baseUnit": "g" },
      { "name": "teaspoon", "baseValue": 3, "baseUnit": "g" }
    ]
  },
  {
    "categoria": "other",
    "name": "baking soda",
    "standardUnit": "g",
    "allowedMeasures": [
      { "name": "g", "baseValue": 1, "baseUnit": "g" },
      { "name": "kg", "baseValue": 1000, "baseUnit": "g" },
      { "name": "teaspoon", "baseValue": 5, "baseUnit": "g" },
      { "name": "pinch", "baseValue": 1, "baseUnit": "g" }
    ]
  },
  {
    "categoria": "other",
    "name": "gelatin",
    "standardUnit": "g",
    "allowedMeasures": [
      { "name": "g", "baseValue": 1, "baseUnit": "g" },
      { "name": "kg", "baseValue": 1000, "baseUnit": "g" },
      { "name": "leaf", "baseValue": 2, "baseUnit": "g" },
      { "name": "packet", "baseValue": 10, "baseUnit": "g" }
    ]
  },
  {
    "categoria": "other",
    "name": "cocoa powder",
    "standardUnit": "g",
    "allowedMeasures": [
      { "name": "g", "baseValue": 1, "baseUnit": "g" },
      { "name": "kg", "baseValue": 1000, "baseUnit": "g" },
      { "name": "tablespoon", "baseValue": 10, "baseUnit": "g" },
      { "name": "teaspoon", "baseValue": 3, "baseUnit": "g" }
    ]
  },
  {
    "categoria": "other",
    "name": "fried tomato sauce",
    "standardUnit": "g",
    "allowedMeasures": [
      { "name": "g", "baseValue": 1, "baseUnit": "g" },
      { "name": "kg", "baseValue": 1000, "baseUnit": "g" },
      { "name": "ml", "baseValue": 1, "baseUnit": "ml" },
      { "name": "l", "baseValue": 1000, "baseUnit": "ml" },
      { "name": "tablespoon", "baseValue": 15, "baseUnit": "g" },
      { "name": "cup", "baseValue": 250, "baseUnit": "g" }
    ]
  },
  {
    "categoria": "other",
    "name": "tomato paste",
    "standardUnit": "g",
    "allowedMeasures": [
      { "name": "g", "baseValue": 1, "baseUnit": "g" },
      { "name": "kg", "baseValue": 1000, "baseUnit": "g" },
      { "name": "tablespoon", "baseValue": 20, "baseUnit": "g" },
      { "name": "teaspoon", "baseValue": 7, "baseUnit": "g" }
    ]
  },
  {
    "categoria": "other",
    "name": "olives",
    "standardUnit": "g",
    "allowedMeasures": [
      { "name": "g", "baseValue": 1, "baseUnit": "g" },
      { "name": "kg", "baseValue": 1000, "baseUnit": "g" },
      { "name": "unit", "baseValue": 3, "baseUnit": "g" },
      { "name": "handfull", "baseValue": 30, "baseUnit": "g" }
    ]
  },
  {
    "categoria": "other",
    "name": "capers",
    "standardUnit": "g",
    "allowedMeasures": [
      { "name": "g", "baseValue": 1, "baseUnit": "g" },
      { "name": "kg", "baseValue": 1000, "baseUnit": "g" },
      { "name": "teaspoon", "baseValue": 5, "baseUnit": "g" },
      { "name": "tablespoon", "baseValue": 15, "baseUnit": "g" }
    ]
  },
  {
    "categoria": "other",
    "name": "bread crumbs",
    "standardUnit": "g",
    "allowedMeasures": [
      { "name": "g", "baseValue": 1, "baseUnit": "g" },
      { "name": "kg", "baseValue": 1000, "baseUnit": "g" }
    ]
  },
  {
    "categoria": "other",
    "name": "chopped tomato",
    "standardUnit": "g",
    "allowedMeasures": [
      { "name": "g", "baseValue": 1, "baseUnit": "g" },
      { "name": "kg", "baseValue": 1000, "baseUnit": "g" }
    ]
  },
  {
    "categoria": "other",
    "name": "mushrooms",
    "standardUnit": "g",
    "allowedMeasures": [
      { "name": "g", "baseValue": 1, "baseUnit": "g" },
      { "name": "kg", "baseValue": 1000, "baseUnit": "g" },
      { "name": "tray", "baseValue": 200, "baseUnit": "g" }
    ]
  },
  {
    "categoria": "other",
    "name": "bread",
    "standardUnit": "unit",
    "allowedMeasures": [
      { "name": "loaf", "baseValue": 1, "baseUnit": "unit" },
      { "name": "dietToast", "baseValue": 0.2, "baseUnit": "unit" }
    ]
  },
  {
    "categoria": "other",
    "name": "toast",
    "standardUnit": "packet",
    "allowedMeasures": [
      { "name": "unit", "baseValue": 0.125, "baseUnit": "unit" },
      { "name": "packet", "baseValue": 1, "baseUnit": "unit" }
    ]
  }
]